pyballistic/__init__.py
pyballistic/_compat.py
pyballistic/conditions.py
pyballistic/constants.py
pyballistic/drag_model.py
pyballistic/drag_tables.py
pyballistic/example.py
pyballistic/exceptions.py
pyballistic/helpers.py
pyballistic/interface.py
pyballistic/interpolation.py
pyballistic/logger.py
pyballistic/munition.py
pyballistic/trajectory_data.py
pyballistic/unit.py
pyballistic/vector.py
pyballistic/assets/.pybc-imperial.toml
pyballistic/assets/.pybc-metrics.toml
pyballistic/assets/.pybc-mixed.toml
pyballistic/engines/__init__.py
pyballistic/engines/base_engine.py
pyballistic/engines/euler.py
pyballistic/engines/rk4.py
pyballistic/engines/scipy_engine.py
pyballistic/engines/velocity_verlet.py
pyballistic/generics/__init__.py
pyballistic/generics/engine.py
pyballistic/visualize/__init__.py
pyballistic/visualize/dataframe.py
pyballistic/visualize/plot.py
pyballistic-2.2.0.dist-info/licenses/LICENSE
pyballistic-2.2.0.dist-info/METADATA
pyballistic-2.2.0.dist-info/WHEEL
pyballistic-2.2.0.dist-info/entry_points.txt
pyballistic-2.2.0.dist-info/top_level.txt
pyballistic-2.2.0.dist-info/RECORD
