Metadata-Version: 2.4
Name: pyballistic
Version: 2.2.0
Summary: LGPL library for small arms ballistic calculations (Python 3)
Author-email: o-murphy <thehelixpg@gmail.com>, dbookstaber <bookstaber@gmail.com>
License:                    GNU LESSER GENERAL PUBLIC LICENSE
Project-URL: Homepage, https://github.com/dbookstaber/pyballistic
Project-URL: Bug Reports, https://github.com/dbookstaber/pyballistic/issues
Project-URL: Source, https://github.com/dbookstaber/pyballistic
Keywords: pyballistic,ballistics,Cython,ballistic calculator,python,ballistic solver
Classifier: Intended Audience :: Developers
Classifier: Natural Language :: English
Classifier: Programming Language :: Python
Classifier: Topic :: Software Development :: Libraries :: Python Modules
Classifier: Programming Language :: Python :: 3
Classifier: Programming Language :: Python :: 3 :: Only
Classifier: Programming Language :: Python :: 3.9
Classifier: Programming Language :: Python :: 3.10
Classifier: Programming Language :: Python :: 3.11
Classifier: Programming Language :: Python :: 3.12
Classifier: Programming Language :: Python :: 3.13
Classifier: Operating System :: OS Independent
Classifier: Programming Language :: Python :: Implementation :: CPython
Requires-Python: >=3.9
License-File: LICENSE
Requires-Dist: typing_extensions>=4.12.2
Requires-Dist: tomli>=2.2.1; python_version < "3.11"
Requires-Dist: Deprecated>=1.2.18
Requires-Dist: pandas>=2.3.1
Provides-Extra: exts
Requires-Dist: pyballistic.exts==2.2.0; extra == "exts"
Provides-Extra: charts
Requires-Dist: matplotlib>=3.9; extra == "charts"
Requires-Dist: pandas>=2.3.0; extra == "charts"
Requires-Dist: numpy>=2; extra == "charts"
Provides-Extra: scipy
Requires-Dist: numpy>=2; extra == "scipy"
Requires-Dist: scipy>=1.13.1; extra == "scipy"
Provides-Extra: dev
Requires-Dist: Cython>=3.0; extra == "dev"
Requires-Dist: build>=1.2.2.post1; extra == "dev"
Requires-Dist: jupyter>=1.1.1; extra == "dev"
Requires-Dist: matplotlib>=3.9; extra == "dev"
Requires-Dist: mypy>=1.15.0; extra == "dev"
Requires-Dist: numpy>=2; extra == "dev"
Requires-Dist: scipy>=1.13.1; extra == "dev"
Requires-Dist: pandas>=2.3.1; extra == "dev"
Requires-Dist: pandas-stubs>=2.2.2.240807; extra == "dev"
Requires-Dist: pylint>=3.3.4; extra == "dev"
Requires-Dist: pytest>=8.3.5; extra == "dev"
Requires-Dist: pytest-cov>=6.0.0; extra == "dev"
Requires-Dist: pytest-xdist>=3.6.1; extra == "dev"
Requires-Dist: scipy-stubs<1.16.0.1,>=1.4.1a3; python_version == "3.10" and extra == "dev"
Requires-Dist: scipy-stubs>=1.16.0.1; python_version >= "3.11" and extra == "dev"
Requires-Dist: types-deprecated>=1.2.15.20250304; extra == "dev"
Requires-Dist: ruff>=0.12.3; extra == "dev"
Provides-Extra: docs
Requires-Dist: mkdocs-mermaid2-plugin; extra == "docs"
Requires-Dist: mkdocs; extra == "docs"
Requires-Dist: mkdocs-exclude; extra == "docs"
Requires-Dist: mkdocs-material[imaging]; extra == "docs"
Requires-Dist: mkdocs-redirects; extra == "docs"
Requires-Dist: mkdocstrings>=0.29.0; extra == "docs"
Requires-Dist: mkdocstrings-python>=1.16.0; extra == "docs"
Requires-Dist: mkdocs-autorefs; extra == "docs"
Requires-Dist: mike; extra == "docs"
Requires-Dist: pydocstyle; extra == "docs"
Requires-Dist: ruff; extra == "docs"
Dynamic: license-file
